audiotranscription/__init__.py
audiotranscription/audio_processing.py
audiotranscription/audio_transcription.py
audiotranscription/speaker_diarization.py
audiotranscription/text_processing.py
audiotranscription-0.1.5.dist-info/METADATA
audiotranscription-0.1.5.dist-info/WHEEL
audiotranscription-0.1.5.dist-info/top_level.txt
audiotranscription-0.1.5.dist-info/RECORD
